evotorch/__init__.py
evotorch/__version.py
evotorch/core.py
evotorch/decorators.py
evotorch/distributions.py
evotorch/logging.py
evotorch/optimizers.py
evotorch/testing.py
evotorch/algorithms/__init__.py
evotorch/algorithms/cmaes.py
evotorch/algorithms/ga.py
evotorch/algorithms/mapelites.py
evotorch/algorithms/pycmaes.py
evotorch/algorithms/searchalgorithm.py
evotorch/algorithms/distributed/__init__.py
evotorch/algorithms/distributed/gaussian.py
evotorch/algorithms/functional/__init__.py
evotorch/algorithms/functional/funcadam.py
evotorch/algorithms/functional/funccem.py
evotorch/algorithms/functional/funcclipup.py
evotorch/algorithms/functional/funcpgpe.py
evotorch/algorithms/functional/funcsgd.py
evotorch/algorithms/functional/misc.py
evotorch/algorithms/restarter/__init__.py
evotorch/algorithms/restarter/modify_restart.py
evotorch/algorithms/restarter/restart.py
evotorch/neuroevolution/__init__.py
evotorch/neuroevolution/baseneproblem.py
evotorch/neuroevolution/gymne.py
evotorch/neuroevolution/neproblem.py
evotorch/neuroevolution/supervisedne.py
evotorch/neuroevolution/vecgymne.py
evotorch/neuroevolution/net/__init__.py
evotorch/neuroevolution/net/functional.py
evotorch/neuroevolution/net/layers.py
evotorch/neuroevolution/net/misc.py
evotorch/neuroevolution/net/multilayered.py
evotorch/neuroevolution/net/parser.py
evotorch/neuroevolution/net/rl.py
evotorch/neuroevolution/net/runningnorm.py
evotorch/neuroevolution/net/runningstat.py
evotorch/neuroevolution/net/statefulmodule.py
evotorch/neuroevolution/net/vecrl.py
evotorch/operators/__init__.py
evotorch/operators/base.py
evotorch/operators/functional.py
evotorch/operators/real.py
evotorch/operators/sequence.py
evotorch/tools/__init__.py
evotorch/tools/cloning.py
evotorch/tools/constraints.py
evotorch/tools/hook.py
evotorch/tools/immutable.py
evotorch/tools/misc.py
evotorch/tools/objectarray.py
evotorch/tools/ranking.py
evotorch/tools/readonlytensor.py
evotorch/tools/recursiveprintable.py
evotorch-0.6.1.dist-info/licenses/LICENSE
evotorch-0.6.1.dist-info/METADATA
evotorch-0.6.1.dist-info/WHEEL
evotorch-0.6.1.dist-info/top_level.txt
evotorch-0.6.1.dist-info/RECORD
