Metadata-Version: 2.4
Name: evotorch
Version: 0.6.1
Summary: EvoTorch is an advanced evolutionary computation library built directly on top of PyTorch, created at NNAISENSE.
Home-page: https://evotorch.ai
Author: Nihat Engin Toklu, Timothy Atkinson, Vojtech Micka, Pawel Liskowski, Rupesh Kumar Srivastava
Author-email: engin@nnaisense.com, timothy@nnaisense.com, vojtech@nnaisense.com, pawel@nnaisense.com, rupesh@nnaisense.com
License: Apache 2.0
Project-URL: Documentation, https://docs.evotorch.ai
Project-URL: Source Code, https://github.com/nnaisense/evotorch
Keywords: python,evolution,neuroevolution,evolutionary computation,genetic algorithm,reinforcement learning
Classifier: Intended Audience :: Developers
Classifier: Intended Audience :: Science/Research
Classifier: Natural Language :: English
Classifier: Operating System :: OS Independent
Classifier: Programming Language :: Python :: 3
Classifier: Programming Language :: Python :: 3.10
Classifier: Programming Language :: Python :: 3.11
Classifier: Programming Language :: Python :: 3.12
Classifier: Programming Language :: Python :: 3.13
Classifier: Topic :: Utilities
Classifier: Topic :: Scientific/Engineering :: Artificial Intelligence
Requires-Python: >=3.10
License-File: LICENSE
Requires-Dist: cma
Requires-Dist: gymnasium
Requires-Dist: matplotlib
Requires-Dist: numpy
Requires-Dist: packaging
Requires-Dist: pandas
Requires-Dist: ray>=1.0
Requires-Dist: torch
Provides-Extra: mlflow
Requires-Dist: mlflow; extra == "mlflow"
Provides-Extra: neptune
Requires-Dist: neptune; extra == "neptune"
Provides-Extra: sacred
Requires-Dist: sacred; extra == "sacred"
Provides-Extra: wandb
Requires-Dist: wandb; extra == "wandb"
Provides-Extra: logging
Requires-Dist: mlflow; extra == "logging"
Requires-Dist: neptune; extra == "logging"
Requires-Dist: sacred; extra == "logging"
Requires-Dist: wandb; extra == "logging"
Provides-Extra: all
Requires-Dist: box2d; extra == "all"
Requires-Dist: pymongo; extra == "all"
Requires-Dist: jupyterlab; extra == "all"
Requires-Dist: mlflow; extra == "all"
Requires-Dist: neptune; extra == "all"
Requires-Dist: sacred; extra == "all"
Requires-Dist: wandb; extra == "all"
Provides-Extra: doc
Requires-Dist: mike; extra == "doc"
Requires-Dist: mkdocs; extra == "doc"
Requires-Dist: mkdocs-gen-files; extra == "doc"
Requires-Dist: mkdocs-literate-nav; extra == "doc"
Requires-Dist: mkdocs-material; extra == "doc"
Requires-Dist: mkdocstrings-python; extra == "doc"
Requires-Dist: nbconvert; extra == "doc"
Requires-Dist: mlflow; extra == "doc"
Requires-Dist: neptune; extra == "doc"
Requires-Dist: sacred; extra == "doc"
Requires-Dist: wandb; extra == "doc"
Provides-Extra: test
Requires-Dist: pytest; extra == "test"
Requires-Dist: pytest-cov; extra == "test"
Provides-Extra: dev
Requires-Dist: black; extra == "dev"
Requires-Dist: flake8; extra == "dev"
Requires-Dist: isort; extra == "dev"
Requires-Dist: pre-commit; extra == "dev"
Requires-Dist: swig; extra == "dev"
Requires-Dist: box2d; extra == "dev"
Requires-Dist: pymongo; extra == "dev"
Requires-Dist: jupyterlab; extra == "dev"
Requires-Dist: mlflow; extra == "dev"
Requires-Dist: neptune; extra == "dev"
Requires-Dist: sacred; extra == "dev"
Requires-Dist: wandb; extra == "dev"
Requires-Dist: pytest; extra == "dev"
Requires-Dist: pytest-cov; extra == "dev"
Requires-Dist: mike; extra == "dev"
Requires-Dist: mkdocs; extra == "dev"
Requires-Dist: mkdocs-gen-files; extra == "dev"
Requires-Dist: mkdocs-literate-nav; extra == "dev"
Requires-Dist: mkdocs-material; extra == "dev"
Requires-Dist: mkdocstrings-python; extra == "dev"
Requires-Dist: nbconvert; extra == "dev"
Requires-Dist: mlflow; extra == "dev"
Requires-Dist: neptune; extra == "dev"
Requires-Dist: sacred; extra == "dev"
Requires-Dist: wandb; extra == "dev"
Dynamic: license-file
